README.rst
setup.py
Omgircd3.egg-info/PKG-INFO
Omgircd3.egg-info/SOURCES.txt
Omgircd3.egg-info/dependency_links.txt
Omgircd3.egg-info/entry_points.txt
Omgircd3.egg-info/top_level.txt
omgircd3/__init__.py
omgircd3/ircd.py
omgircd3/ircdreload.py
omgircd3.egg-info/PKG-INFO
omgircd3.egg-info/SOURCES.txt
omgircd3.egg-info/dependency_links.txt
omgircd3.egg-info/entry_points.txt
omgircd3.egg-info/top_level.txt
tests/__init__.py
tests/test_channel_finders.py
tests/test_config_loader.py
tests/test_server_finders.py
tests/test_validators.py