Metadata-Version: 1.2
Name: omgircd3
Version: 1.0.0
Summary: A Python3 IRC server/daemon
Home-page: https://github.com/brunobord/omgircd3
Author: Bruno Bord
Author-email: bruno@jehaisleprintemps.net
License: ISC
Platform: UNKNOWN
Classifier: Development Status :: 3 - Alpha
Classifier: Operating System :: OS Independent
Classifier: Topic :: Communications :: Chat :: Internet Relay Chat
Classifier: License :: OSI Approved :: ISC License (ISCL)
Classifier: Programming Language :: Python :: 3
Classifier: Programming Language :: Python :: 3.6
Requires-Python: ~=3.6
